heaptree/__init__.py
heaptree/client.py
heaptree/enums.py
heaptree/exceptions.py
heaptree/response_wrappers.py
heaptree_test_sdk-105151515.dist-info/licenses/LICENSE
heaptree_test_sdk-105151515.dist-info/METADATA
heaptree_test_sdk-105151515.dist-info/WHEEL
heaptree_test_sdk-105151515.dist-info/top_level.txt
heaptree_test_sdk-105151515.dist-info/RECORD
