Metadata-Version: 2.4
Name: heaptree-test-sdk
Version: 105151515
Summary: Heaptree | Secure Cloud Instances to Enhance Your AI at Scale
Author-email: heaptree <heaptreehq@gmail.com>
License-Expression: MIT
Project-URL: Homepage, https://heaptree.com
Classifier: Programming Language :: Python :: 3
Classifier: Operating System :: OS Independent
Requires-Python: >=3.9
License-File: LICENSE
Requires-Dist: requests>=2.25.1
Dynamic: license-file
